README.rst
setup.py
src/drf_depaginator.py
src/drf_depaginator.egg-info/PKG-INFO
src/drf_depaginator.egg-info/SOURCES.txt
src/drf_depaginator.egg-info/dependency_links.txt
src/drf_depaginator.egg-info/top_level.txt